raydp/__init__.py
raydp/context.py
raydp/estimator.py
raydp/ray_cluster_resources.py
raydp/services.py
raydp/utils.py
raydp/versions.py
raydp/bin/raydp-submit
raydp/jars/raydp-1.7.0-SNAPSHOT.jar
raydp/jars/raydp-agent-1.7.0-SNAPSHOT.jar
raydp/jars/raydp-shims-common-1.7.0-SNAPSHOT.jar
raydp/jars/raydp-shims-spark322-1.7.0-SNAPSHOT.jar
raydp/jars/raydp-shims-spark330-1.7.0-SNAPSHOT.jar
raydp/jars/raydp-shims-spark340-1.7.0-SNAPSHOT.jar
raydp/jars/raydp-shims-spark350-1.7.0-SNAPSHOT.jar
raydp/mpi/__init__.py
raydp/mpi/constants.py
raydp/mpi/mpi_job.py
raydp/mpi/mpi_worker.py
raydp/mpi/utils.py
raydp/mpi/network/__init__.py
raydp/mpi/network/network_pb2.py
raydp/mpi/network/network_pb2_grpc.py
raydp/spark/__init__.py
raydp/spark/dataset.py
raydp/spark/interfaces.py
raydp/spark/parallel_iterator_worker.py
raydp/spark/ray_cluster.py
raydp/spark/ray_cluster_master.py
raydp/tf/__init__.py
raydp/tf/estimator.py
raydp/torch/__init__.py
raydp/torch/config.py
raydp/torch/estimator.py
raydp/torch/torch_metrics.py
raydp/torch/torch_ml_dataset.py
raydp/xgboost/__init__.py
raydp/xgboost/estimator.py
raydp_nightly-2025.12.4.dev0.dist-info/METADATA
raydp_nightly-2025.12.4.dev0.dist-info/WHEEL
raydp_nightly-2025.12.4.dev0.dist-info/top_level.txt
raydp_nightly-2025.12.4.dev0.dist-info/RECORD
