Metadata-Version: 2.1
Name: raydp-nightly
Version: 2025.12.4.dev0
Summary: RayDP: Distributed Data Processing on Ray
Home-page: https://github.com/ray-project/raydp
Author: RayDP Developers
Author-email: raydp-dev@googlegroups.com
License: Apache 2.0
Keywords: raydp spark ray distributed data-processing
Classifier: License :: OSI Approved :: Apache Software License
Classifier: Programming Language :: Python :: 3.8
Classifier: Programming Language :: Python :: 3.9
Classifier: Programming Language :: Python :: 3.10
Requires-Python: >=3.6
Requires-Dist: numpy
Requires-Dist: pandas>=1.1.4
Requires-Dist: psutil
Requires-Dist: pyarrow>=4.0.1
Requires-Dist: ray>=2.1.0
Requires-Dist: pyspark<=3.5.7,>=3.1.1
Requires-Dist: netifaces
Requires-Dist: protobuf>3.19.5
